worf/__init__.py
worf/assigns.py
worf/casing.py
worf/conf.py
worf/exceptions.py
worf/fields.py
worf/filters.py
worf/lookups.py
worf/permissions.py
worf/renderers.py
worf/serializers.py
worf/settings.py
worf/shortcuts.py
worf/templates/worf/api.html
worf/templates/worf/base.html
worf/testing.py
worf/validators.py
worf/views/__init__.py
worf/views/action.py
worf/views/base.py
worf/views/create.py
worf/views/delete.py
worf/views/detail.py
worf/views/errors.py
worf/views/list.py
worf/views/update.py
worf-0.5.30.dist-info/LICENSE.md
worf-0.5.30.dist-info/METADATA
worf-0.5.30.dist-info/WHEEL
worf-0.5.30.dist-info/RECORD
