Metadata-Version: 2.1
Name: worf
Version: 0.5.30
Summary: Wade's own REST Framework: A more Djangonic approach to REST APIs
Home-page: https://github.com/gundotio/worf
License: MIT
Keywords: django,rest,framework,api
Author: Wade Williams
Author-email: wade@wadewilliams.com
Requires-Python: >=3.9,<4.0
Classifier: Development Status :: 4 - Beta
Classifier: Environment :: Web Environment
Classifier: Framework :: Django
Classifier: Framework :: Django :: 3
Classifier: Framework :: Django :: 3.2
Classifier: Framework :: Django :: 4
Classifier: Framework :: Django :: 4.0
Classifier: Framework :: Django :: 4.1
Classifier: Intended Audience :: Developers
Classifier: License :: OSI Approved :: MIT License
Classifier: Programming Language :: Python
Classifier: Programming Language :: Python :: 3
Classifier: Programming Language :: Python :: 3.9
Classifier: Programming Language :: Python :: 3.10
Classifier: Programming Language :: Python :: 3.11
Classifier: Programming Language :: Python :: 3 :: Only
Classifier: Topic :: Internet :: WWW/HTTP
Classifier: Topic :: Internet :: WWW/HTTP :: Dynamic Content
Classifier: Topic :: Software Development :: Libraries :: Python Modules
Requires-Dist: dj-url-filter (>=0.4.4,<0.5.0)
Requires-Dist: django (>=3.0.0,<4.2)
Requires-Dist: marshmallow (>=3.18,<4.0)
